zekiakgul/__init__.py
zekiakgul/statistics.py
zekiakgul-0.0.1.dist-info/licenses/LICENSE
zekiakgul-0.0.1.dist-info/METADATA
zekiakgul-0.0.1.dist-info/WHEEL
zekiakgul-0.0.1.dist-info/top_level.txt
zekiakgul-0.0.1.dist-info/RECORD
