Metadata-Version: 2.4
Name: zekiakgul
Version: 0.0.1
Summary: A simple package for calculating statistics.
Author-email: Zeki Akgul <zeki.akgul5835@gmail.com>
Project-URL: Homepage, https://github.com/zexy2/zekiakgul
Keywords: zekiakgul,statistics
Classifier: Development Status :: 3 - Alpha
Classifier: Intended Audience :: Developers
Classifier: License :: OSI Approved :: MIT License
Classifier: Programming Language :: Python :: 3
Classifier: Operating System :: OS Independent
Requires-Python: >=3.6.0
License-File: LICENSE
Dynamic: license-file
